nonebot_plugin_xiaohongshu/__init__.py
nonebot_plugin_xiaohongshu/config.py
nonebot_plugin_xiaohongshu-0.1.4.dist-info/METADATA
nonebot_plugin_xiaohongshu-0.1.4.dist-info/WHEEL
nonebot_plugin_xiaohongshu-0.1.4.dist-info/licenses/LICENSE
nonebot_plugin_xiaohongshu-0.1.4.dist-info/RECORD
