Metadata-Version: 2.4
Name: nonebot-plugin-xiaohongshu
Version: 0.1.4
Summary: 一个用于解析小红书链接的 nonebot2 插件
License: MIT
License-File: LICENSE
Keywords: nonebot,nonebot2,xiaohongshu,xhs,spider,image,video
Author: bytedo
Author-email: 49683326+bytedo@users.noreply.github.com
Requires-Python: >=3.9,<4.0
Classifier: License :: OSI Approved :: MIT License
Classifier: Operating System :: OS Independent
Classifier: Programming Language :: Python :: 3
Classifier: Programming Language :: Python :: 3.9
Classifier: Programming Language :: Python :: 3.10
Classifier: Programming Language :: Python :: 3.11
Classifier: Programming Language :: Python :: 3.12
Classifier: Programming Language :: Python :: 3.13
Classifier: Programming Language :: Python :: 3.14
Requires-Dist: httpx (>=0.23.0)
Requires-Dist: nonebot-adapter-onebot (>=2.0.0,<3.0.0)
Requires-Dist: nonebot2 (>=2.3.0,<3.0.0)
Requires-Dist: pydantic (>=1.10.0)
Project-URL: Documentation, https://github.com/bytedo/nonebot-plugin-xiaohongshu/blob/main/README.md
Project-URL: Homepage, https://github.com/bytedo/nonebot-plugin-xiaohongshu
Project-URL: Repository, https://github.com/bytedo/nonebot-plugin-xiaohongshu
